nocodb/Base.py
nocodb/Column.py
nocodb/Record.py
nocodb/Table.py
nocodb/__init__.py
nocodb_api-0.0.4.dist-info/LICENSE
nocodb_api-0.0.4.dist-info/METADATA
nocodb_api-0.0.4.dist-info/WHEEL
nocodb_api-0.0.4.dist-info/top_level.txt
nocodb_api-0.0.4.dist-info/RECORD
