Metadata-Version: 2.1
Name: nocodb-api
Version: 0.0.4
Summary: Python client for NocoDB API v2
Author-email: infeeeee <gyetpet@mailbox.org>
Maintainer-email: infeeeee <gyetpet@mailbox.org>
License:                     GNU GENERAL PUBLIC LICENSE
Project-URL: homepage, https://github.com/infeeeee/nocodb-api
Project-URL: documentation, https://github.com/infeeeee/nocodb-api
Project-URL: repository, https://github.com/infeeeee/nocodb-api
Project-URL: changelog, https://github.com/infeeeee/nocodb-api/releases
Classifier: Development Status :: 3 - Alpha
Classifier: Programming Language :: Python
Classifier: License :: OSI Approved :: GNU General Public License v3 (GPLv3)
Requires-Python: >=3.8
License-File: LICENSE
Requires-Dist: requests
Provides-Extra: doc
Requires-Dist: pdoc; extra == "doc"
